neuroworkflow/__init__.py
neuroworkflow/base.py
neuroworkflow-0.1.2b0.dist-info/METADATA
neuroworkflow-0.1.2b0.dist-info/WHEEL
neuroworkflow-0.1.2b0.dist-info/licenses/LICENSE
neuroworkflow-0.1.2b0.dist-info/RECORD
